<BackupInst xmlns="http://www.microsoft.com/GroupPolicy/GPOOperations/Manifest"><GPOGuid><![CDATA[{92E34F8F-1174-4CC5-9138-EA5A1D9BE24D}]]></GPOGuid><GPODomain><![CDATA[siemlab.dk]]></GPODomain><GPODomainGuid><![CDATA[{65102a9a-9054-4fc6-b7dc-723f208a6a96}]]></GPODomainGuid><GPODomainController><![CDATA[dc1.siemlab.dk]]></GPODomainController><BackupTime><![CDATA[2018-04-26T18:13:17]]></BackupTime><ID><![CDATA[{78057AD2-C8D7-4309-8CA2-3CCCDA10CFE3}]]></ID><Comment><![CDATA[Custom Event Channel Permissions]]></Comment><GPODisplayName><![CDATA[Custom Event Channel Permissions]]></GPODisplayName></BackupInst>
